[{"fecha": "2025-08-10", "prob": 0.7256, "cuota": 2.33, "ev": 0.6908, "gano": 0, "lado": "under"}, {"fecha": "2025-08-10", "prob": 0.6092, "cuota": 2.0, "ev": 0.2183, "gano": 0, "lado": "under"}, {"fecha": "2025-08-16", "prob": 0.511, "cuota": 2.48, "ev": 0.2672, "gano": 0, "lado": "under"}, {"fecha": "2025-08-16", "prob": 0.6503, "cuota": 1.81, "ev": 0.1771, "gano": 0, "lado": "under"}, {"fecha": "2025-08-16", "prob": 0.7273, "cuota": 2.06, "ev": 0.4981, "gano": 0, "lado": "under"}, {"fecha": "2025-08-17", "prob": 0.5666, "cuota": 1.77, "ev": 0.0029, "gano": 1, "lado": "over"}, {"fecha": "2025-08-17", "prob": 0.4767, "cuota": 2.83, "ev": 0.349, "gano": 1, "lado": "under"}, {"fecha": "2025-08-17", "prob": 0.4884, "cuota": 3.01, "ev": 0.4701, "gano": 0, "lado": "under"}, {"fecha": "2025-08-23", "prob": 0.4594, "cuota": 2.43, "ev": 0.1164, "gano": 0, "lado": "under"}, {"fecha": "2025-08-24", "prob": 0.7786, "cuota": 1.34, "ev": 0.0434, "gano": 0, "lado": "over"}, {"fecha": "2025-08-24", "prob": 0.601, "cuota": 1.96, "ev": 0.1779, "gano": 0, "lado": "under"}, {"fecha": "2025-08-24", "prob": 0.5386, "cuota": 2.39, "ev": 0.2872, "gano": 0, "lado": "under"}, {"fecha": "2025-08-24", "prob": 0.5964, "cuota": 2.49, "ev": 0.4852, "gano": 0, "lado": "under"}, {"fecha": "2025-08-29", "prob": 0.6194, "cuota": 1.99, "ev": 0.2326, "gano": 0, "lado": "under"}, {"fecha": "2025-08-30", "prob": 0.5424, "cuota": 2.15, "ev": 0.1662, "gano": 1, "lado": "under"}, {"fecha": "2025-08-30", "prob": 0.4859, "cuota": 2.51, "ev": 0.2195, "gano": 0, "lado": "under"}, {"fecha": "2025-08-30", "prob": 0.5351, "cuota": 2.9, "ev": 0.5516, "gano": 1, "lado": "under"}, {"fecha": "2025-08-31", "prob": 0.685, "cuota": 2.24, "ev": 0.5343, "gano": 0, "lado": "under"}, {"fecha": "2025-08-31", "prob": 0.6609, "cuota": 1.67, "ev": 0.1037, "gano": 0, "lado": "over"}, {"fecha": "2025-08-31", "prob": 0.47, "cuota": 2.28, "ev": 0.0715, "gano": 0, "lado": "under"}, {"fecha": "2025-08-31", "prob": 0.6771, "cuota": 1.98, "ev": 0.3408, "gano": 1, "lado": "under"}, {"fecha": "2025-09-13", "prob": 0.389, "cuota": 2.64, "ev": 0.0269, "gano": 0, "lado": "under"}, {"fecha": "2025-09-13", "prob": 0.6892, "cuota": 2.89, "ev": 0.9917, "gano": 1, "lado": "under"}, {"fecha": "2025-09-13", "prob": 0.571, "cuota": 3.08, "ev": 0.7587, "gano": 0, "lado": "under"}, {"fecha": "2025-09-13", "prob": 0.4863, "cuota": 3.31, "ev": 0.6097, "gano": 0, "lado": "under"}, {"fecha": "2025-09-13", "prob": 0.6939, "cuota": 2.19, "ev": 0.5196, "gano": 0, "lado": "under"}, {"fecha": "2025-09-14", "prob": 0.5694, "cuota": 2.38, "ev": 0.3552, "gano": 1, "lado": "under"}, {"fecha": "2025-09-14", "prob": 0.5389, "cuota": 2.46, "ev": 0.3257, "gano": 0, "lado": "under"}, {"fecha": "2025-09-14", "prob": 0.5778, "cuota": 1.74, "ev": 0.0053, "gano": 1, "lado": "over"}, {"fecha": "2025-09-17", "prob": 0.5411, "cuota": 2.7, "ev": 0.461, "gano": 1, "lado": "under"}, {"fecha": "2025-09-19", "prob": 0.5787, "cuota": 2.21, "ev": 0.2789, "gano": 0, "lado": "under"}, {"fecha": "2025-09-20", "prob": 0.6014, "cuota": 1.77, "ev": 0.0645, "gano": 0, "lado": "over"}, {"fecha": "2025-09-20", "prob": 0.6063, "cuota": 1.99, "ev": 0.2066, "gano": 1, "lado": "under"}, {"fecha": "2025-09-20", "prob": 0.6184, "cuota": 2.02, "ev": 0.2493, "gano": 0, "lado": "under"}, {"fecha": "2025-09-20", "prob": 0.7327, "cuota": 2.45, "ev": 0.7951, "gano": 0, "lado": "under"}, {"fecha": "2025-09-21", "prob": 0.6927, "cuota": 2.38, "ev": 0.6486, "gano": 0, "lado": "under"}, {"fecha": "2025-09-21", "prob": 0.4966, "cuota": 2.51, "ev": 0.2465, "gano": 0, "lado": "under"}, {"fecha": "2025-09-21", "prob": 0.3922, "cuota": 3.05, "ev": 0.1962, "gano": 0, "lado": "under"}, {"fecha": "2025-09-21", "prob": 0.6532, "cuota": 2.14, "ev": 0.3978, "gano": 1, "lado": "under"}, {"fecha": "2025-09-24", "prob": 0.4575, "cuota": 2.67, "ev": 0.2215, "gano": 0, "lado": "under"}, {"fecha": "2025-09-26", "prob": 0.6494, "cuota": 2.24, "ev": 0.4546, "gano": 0, "lado": "under"}, {"fecha": "2025-09-27", "prob": 0.7566, "cuota": 1.63, "ev": 0.2333, "gano": 1, "lado": "over"}, {"fecha": "2025-09-27", "prob": 0.7267, "cuota": 2.17, "ev": 0.5769, "gano": 0, "lado": "under"}, {"fecha": "2025-09-28", "prob": 0.5493, "cuota": 1.98, "ev": 0.0876, "gano": 1, "lado": "under"}, {"fecha": "2025-09-28", "prob": 0.7641, "cuota": 1.4, "ev": 0.0698, "gano": 1, "lado": "over"}, {"fecha": "2025-09-28", "prob": 0.7127, "cuota": 2.28, "ev": 0.6248, "gano": 0, "lado": "under"}, {"fecha": "2025-09-28", "prob": 0.5103, "cuota": 2.15, "ev": 0.0972, "gano": 0, "lado": "under"}, {"fecha": "2025-10-03", "prob": 0.6832, "cuota": 1.78, "ev": 0.2161, "gano": 0, "lado": "under"}, {"fecha": "2025-10-04", "prob": 0.7139, "cuota": 1.62, "ev": 0.1565, "gano": 0, "lado": "over"}, {"fecha": "2025-10-04", "prob": 0.5957, "cuota": 2.32, "ev": 0.3821, "gano": 0, "lado": "under"}, {"fecha": "2025-10-04", "prob": 0.5745, "cuota": 3.26, "ev": 0.873, "gano": 0, "lado": "under"}, {"fecha": "2025-10-05", "prob": 0.4385, "cuota": 2.51, "ev": 0.1007, "gano": 0, "lado": "under"}, {"fecha": "2025-10-05", "prob": 0.7783, "cuota": 2.31, "ev": 0.7978, "gano": 0, "lado": "under"}, {"fecha": "2025-10-05", "prob": 0.3906, "cuota": 2.96, "ev": 0.1562, "gano": 1, "lado": "under"}, {"fecha": "2025-10-05", "prob": 0.576, "cuota": 2.62, "ev": 0.5091, "gano": 0, "lado": "under"}, {"fecha": "2025-10-18", "prob": 0.5961, "cuota": 2.08, "ev": 0.2399, "gano": 0, "lado": "under"}, {"fecha": "2025-10-18", "prob": 0.6974, "cuota": 2.41, "ev": 0.6808, "gano": 0, "lado": "under"}, {"fecha": "2025-10-18", "prob": 0.564, "cuota": 4.03, "ev": 1.2728, "gano": 0, "lado": "under"}, {"fecha": "2025-10-18", "prob": 0.4453, "cuota": 2.56, "ev": 0.1399, "gano": 0, "lado": "under"}, {"fecha": "2025-10-19", "prob": 0.6297, "cuota": 2.0, "ev": 0.2594, "gano": 1, "lado": "under"}, {"fecha": "2025-10-19", "prob": 0.5927, "cuota": 2.08, "ev": 0.2328, "gano": 1, "lado": "under"}, {"fecha": "2025-10-19", "prob": 0.5987, "cuota": 2.67, "ev": 0.5986, "gano": 0, "lado": "under"}, {"fecha": "2025-10-19", "prob": 0.8087, "cuota": 2.33, "ev": 0.8842, "gano": 0, "lado": "under"}, {"fecha": "2025-10-25", "prob": 0.5728, "cuota": 2.0, "ev": 0.1456, "gano": 1, "lado": "over"}, {"fecha": "2025-10-25", "prob": 0.5975, "cuota": 2.4, "ev": 0.4341, "gano": 1, "lado": "under"}, {"fecha": "2025-10-25", "prob": 0.6823, "cuota": 2.15, "ev": 0.467, "gano": 0, "lado": "under"}, {"fecha": "2025-10-25", "prob": 0.6088, "cuota": 2.3, "ev": 0.4003, "gano": 0, "lado": "under"}, {"fecha": "2025-10-26", "prob": 0.7593, "cuota": 2.44, "ev": 0.8528, "gano": 0, "lado": "under"}, {"fecha": "2025-10-26", "prob": 0.6463, "cuota": 2.79, "ev": 0.803, "gano": 0, "lado": "under"}, {"fecha": "2025-10-26", "prob": 0.6979, "cuota": 2.18, "ev": 0.5214, "gano": 0, "lado": "under"}, {"fecha": "2025-10-31", "prob": 0.5028, "cuota": 4.05, "ev": 1.0364, "gano": 0, "lado": "under"}, {"fecha": "2025-11-01", "prob": 0.6448, "cuota": 2.67, "ev": 0.7217, "gano": 1, "lado": "under"}, {"fecha": "2025-11-01", "prob": 0.6348, "cuota": 3.87, "ev": 1.4567, "gano": 0, "lado": "under"}, {"fecha": "2025-11-01", "prob": 0.6999, "cuota": 2.21, "ev": 0.5468, "gano": 1, "lado": "under"}, {"fecha": "2025-11-01", "prob": 0.625, "cuota": 2.12, "ev": 0.325, "gano": 0, "lado": "under"}, {"fecha": "2025-11-02", "prob": 0.6434, "cuota": 1.76, "ev": 0.1323, "gano": 0, "lado": "over"}, {"fecha": "2025-11-02", "prob": 0.8115, "cuota": 2.19, "ev": 0.7771, "gano": 0, "lado": "under"}, {"fecha": "2025-11-02", "prob": 0.5376, "cuota": 2.54, "ev": 0.3655, "gano": 1, "lado": "under"}, {"fecha": "2025-11-02", "prob": 0.5537, "cuota": 2.27, "ev": 0.2569, "gano": 1, "lado": "under"}, {"fecha": "2025-11-07", "prob": 0.5817, "cuota": 2.5, "ev": 0.4543, "gano": 1, "lado": "under"}, {"fecha": "2025-11-08", "prob": 0.5924, "cuota": 2.35, "ev": 0.3922, "gano": 0, "lado": "under"}, {"fecha": "2025-11-08", "prob": 0.6016, "cuota": 2.12, "ev": 0.2754, "gano": 1, "lado": "under"}, {"fecha": "2025-11-08", "prob": 0.6078, "cuota": 2.2, "ev": 0.3372, "gano": 1, "lado": "under"}, {"fecha": "2025-11-09", "prob": 0.6373, "cuota": 3.16, "ev": 1.014, "gano": 0, "lado": "under"}, {"fecha": "2025-11-09", "prob": 0.7339, "cuota": 1.4, "ev": 0.0275, "gano": 1, "lado": "over"}, {"fecha": "2025-11-09", "prob": 0.6154, "cuota": 1.64, "ev": 0.0093, "gano": 0, "lado": "over"}, {"fecha": "2025-11-09", "prob": 0.5354, "cuota": 2.15, "ev": 0.1511, "gano": 0, "lado": "under"}, {"fecha": "2025-11-22", "prob": 0.4637, "cuota": 3.16, "ev": 0.4653, "gano": 0, "lado": "under"}, {"fecha": "2025-11-22", "prob": 0.8619, "cuota": 2.23, "ev": 0.922, "gano": 0, "lado": "under"}, {"fecha": "2025-11-22", "prob": 0.652, "cuota": 3.29, "ev": 1.145, "gano": 1, "lado": "under"}, {"fecha": "2025-11-22", "prob": 0.5802, "cuota": 1.8, "ev": 0.0443, "gano": 0, "lado": "over"}, {"fecha": "2025-11-22", "prob": 0.6245, "cuota": 2.24, "ev": 0.3989, "gano": 1, "lado": "under"}, {"fecha": "2025-11-23", "prob": 0.4693, "cuota": 2.98, "ev": 0.3984, "gano": 0, "lado": "under"}, {"fecha": "2025-11-23", "prob": 0.7308, "cuota": 2.18, "ev": 0.5931, "gano": 0, "lado": "under"}, {"fecha": "2025-11-23", "prob": 0.7345, "cuota": 1.48, "ev": 0.087, "gano": 1, "lado": "over"}, {"fecha": "2025-11-23", "prob": 0.6845, "cuota": 1.72, "ev": 0.1773, "gano": 0, "lado": "over"}, {"fecha": "2025-11-28", "prob": 0.7067, "cuota": 1.49, "ev": 0.0529, "gano": 1, "lado": "over"}, {"fecha": "2025-11-29", "prob": 0.6106, "cuota": 2.18, "ev": 0.3312, "gano": 1, "lado": "under"}, {"fecha": "2025-11-30", "prob": 0.5784, "cuota": 1.77, "ev": 0.0238, "gano": 1, "lado": "over"}, {"fecha": "2025-11-30", "prob": 0.2806, "cuota": 4.97, "ev": 0.3944, "gano": 0, "lado": "under"}, {"fecha": "2025-11-30", "prob": 0.6304, "cuota": 2.67, "ev": 0.6832, "gano": 0, "lado": "under"}, {"fecha": "2025-11-30", "prob": 0.5449, "cuota": 2.36, "ev": 0.2859, "gano": 1, "lado": "under"}, {"fecha": "2025-12-02", "prob": 0.5468, "cuota": 2.13, "ev": 0.1646, "gano": 1, "lado": "under"}, {"fecha": "2025-12-06", "prob": 0.7505, "cuota": 3.66, "ev": 1.7467, "gano": 0, "lado": "under"}, {"fecha": "2025-12-06", "prob": 0.5081, "cuota": 2.08, "ev": 0.0569, "gano": 0, "lado": "under"}, {"fecha": "2025-12-06", "prob": 0.5351, "cuota": 3.27, "ev": 0.7499, "gano": 1, "lado": "under"}, {"fecha": "2025-12-06", "prob": 0.4505, "cuota": 2.22, "ev": 0.0001, "gano": 1, "lado": "under"}, {"fecha": "2025-12-07", "prob": 0.5602, "cuota": 2.98, "ev": 0.6695, "gano": 0, "lado": "under"}, {"fecha": "2025-12-07", "prob": 0.786, "cuota": 1.99, "ev": 0.5642, "gano": 1, "lado": "under"}, {"fecha": "2025-12-07", "prob": 0.6918, "cuota": 1.89, "ev": 0.3075, "gano": 1, "lado": "under"}, {"fecha": "2025-12-07", "prob": 0.4475, "cuota": 2.92, "ev": 0.3068, "gano": 0, "lado": "under"}, {"fecha": "2025-12-13", "prob": 0.6962, "cuota": 2.47, "ev": 0.7197, "gano": 0, "lado": "under"}, {"fecha": "2025-12-13", "prob": 0.4917, "cuota": 4.72, "ev": 1.3208, "gano": 0, "lado": "under"}, {"fecha": "2025-12-13", "prob": 0.7007, "cuota": 2.54, "ev": 0.7799, "gano": 0, "lado": "under"}, {"fecha": "2025-12-13", "prob": 0.6234, "cuota": 2.1, "ev": 0.3092, "gano": 1, "lado": "under"}, {"fecha": "2025-12-14", "prob": 0.6991, "cuota": 2.37, "ev": 0.6568, "gano": 1, "lado": "under"}, {"fecha": "2025-12-14", "prob": 0.6306, "cuota": 1.85, "ev": 0.1666, "gano": 1, "lado": "under"}, {"fecha": "2025-12-14", "prob": 0.4379, "cuota": 2.38, "ev": 0.0421, "gano": 0, "lado": "under"}, {"fecha": "2025-12-20", "prob": 0.6287, "cuota": 2.26, "ev": 0.4209, "gano": 0, "lado": "under"}, {"fecha": "2025-12-20", "prob": 0.6962, "cuota": 1.59, "ev": 0.1069, "gano": 1, "lado": "over"}, {"fecha": "2025-12-20", "prob": 0.5214, "cuota": 2.01, "ev": 0.048, "gano": 1, "lado": "under"}, {"fecha": "2025-12-20", "prob": 0.7393, "cuota": 2.72, "ev": 1.011, "gano": 0, "lado": "under"}, {"fecha": "2025-12-21", "prob": 0.6039, "cuota": 2.34, "ev": 0.4131, "gano": 1, "lado": "under"}, {"fecha": "2025-12-21", "prob": 0.5612, "cuota": 2.34, "ev": 0.3132, "gano": 0, "lado": "under"}, {"fecha": "2025-12-21", "prob": 0.6414, "cuota": 2.02, "ev": 0.2956, "gano": 1, "lado": "under"}, {"fecha": "2025-12-21", "prob": 0.5185, "cuota": 2.23, "ev": 0.1561, "gano": 1, "lado": "under"}, {"fecha": "2026-01-10", "prob": 0.5394, "cuota": 3.28, "ev": 0.7691, "gano": 1, "lado": "under"}, {"fecha": "2026-01-10", "prob": 0.6152, "cuota": 3.9, "ev": 1.3994, "gano": 0, "lado": "under"}, {"fecha": "2026-01-10", "prob": 0.8051, "cuota": 1.43, "ev": 0.1512, "gano": 0, "lado": "over"}, {"fecha": "2026-01-11", "prob": 0.7861, "cuota": 2.07, "ev": 0.6272, "gano": 0, "lado": "under"}, {"fecha": "2026-01-11", "prob": 0.6644, "cuota": 1.53, "ev": 0.0165, "gano": 1, "lado": "over"}, {"fecha": "2026-01-11", "prob": 0.6482, "cuota": 2.18, "ev": 0.413, "gano": 1, "lado": "under"}, {"fecha": "2026-01-11", "prob": 0.7018, "cuota": 1.6, "ev": 0.123, "gano": 1, "lado": "over"}, {"fecha": "2026-01-17", "prob": 0.6186, "cuota": 2.49, "ev": 0.5404, "gano": 0, "lado": "under"}, {"fecha": "2026-01-17", "prob": 0.7778, "cuota": 2.02, "ev": 0.5711, "gano": 0, "lado": "under"}, {"fecha": "2026-01-17", "prob": 0.7237, "cuota": 1.44, "ev": 0.0422, "gano": 1, "lado": "over"}, {"fecha": "2026-01-17", "prob": 0.6643, "cuota": 2.04, "ev": 0.3551, "gano": 0, "lado": "under"}, {"fecha": "2026-01-17", "prob": 0.439, "cuota": 2.51, "ev": 0.102, "gano": 0, "lado": "under"}, {"fecha": "2026-01-18", "prob": 0.407, "cuota": 2.69, "ev": 0.0948, "gano": 0, "lado": "under"}, {"fecha": "2026-01-18", "prob": 0.648, "cuota": 2.25, "ev": 0.4579, "gano": 1, "lado": "under"}, {"fecha": "2026-01-18", "prob": 0.5275, "cuota": 2.01, "ev": 0.0603, "gano": 0, "lado": "under"}, {"fecha": "2026-01-21", "prob": 0.7273, "cuota": 2.62, "ev": 0.9055, "gano": 1, "lado": "under"}, {"fecha": "2026-01-24", "prob": 0.6127, "cuota": 2.69, "ev": 0.6481, "gano": 1, "lado": "under"}, {"fecha": "2026-01-24", "prob": 0.7131, "cuota": 2.78, "ev": 0.9823, "gano": 0, "lado": "under"}, {"fecha": "2026-01-24", "prob": 0.7074, "cuota": 1.46, "ev": 0.0328, "gano": 1, "lado": "over"}, {"fecha": "2026-01-24", "prob": 0.6214, "cuota": 2.48, "ev": 0.5411, "gano": 1, "lado": "under"}, {"fecha": "2026-01-25", "prob": 0.3444, "cuota": 3.17, "ev": 0.0917, "gano": 0, "lado": "under"}, {"fecha": "2026-01-25", "prob": 0.6888, "cuota": 1.91, "ev": 0.3156, "gano": 0, "lado": "under"}, {"fecha": "2026-01-25", "prob": 0.5987, "cuota": 2.17, "ev": 0.2992, "gano": 1, "lado": "under"}, {"fecha": "2026-01-25", "prob": 0.6439, "cuota": 1.82, "ev": 0.1719, "gano": 0, "lado": "over"}, {"fecha": "2026-01-30", "prob": 0.7219, "cuota": 1.76, "ev": 0.2706, "gano": 0, "lado": "under"}, {"fecha": "2026-01-31", "prob": 0.5597, "cuota": 2.06, "ev": 0.1531, "gano": 1, "lado": "under"}, {"fecha": "2026-01-31", "prob": 0.8547, "cuota": 2.1, "ev": 0.7949, "gano": 0, "lado": "under"}, {"fecha": "2026-02-01", "prob": 0.6383, "cuota": 2.25, "ev": 0.4362, "gano": 0, "lado": "under"}, {"fecha": "2026-02-01", "prob": 0.5738, "cuota": 2.79, "ev": 0.6009, "gano": 0, "lado": "under"}, {"fecha": "2026-02-01", "prob": 0.7584, "cuota": 2.02, "ev": 0.5321, "gano": 1, "lado": "under"}, {"fecha": "2026-02-06", "prob": 0.6476, "cuota": 1.87, "ev": 0.211, "gano": 1, "lado": "under"}, {"fecha": "2026-02-07", "prob": 0.7281, "cuota": 2.04, "ev": 0.4854, "gano": 0, "lado": "under"}, {"fecha": "2026-02-07", "prob": 0.7917, "cuota": 2.43, "ev": 0.9239, "gano": 0, "lado": "under"}, {"fecha": "2026-02-07", "prob": 0.8124, "cuota": 2.32, "ev": 0.8849, "gano": 0, "lado": "under"}, {"fecha": "2026-02-07", "prob": 0.6196, "cuota": 2.24, "ev": 0.3878, "gano": 0, "lado": "under"}, {"fecha": "2026-02-08", "prob": 0.6914, "cuota": 2.22, "ev": 0.5349, "gano": 1, "lado": "under"}, {"fecha": "2026-02-08", "prob": 0.5715, "cuota": 2.26, "ev": 0.2916, "gano": 1, "lado": "under"}, {"fecha": "2026-02-08", "prob": 0.5287, "cuota": 2.61, "ev": 0.38, "gano": 0, "lado": "under"}, {"fecha": "2026-02-08", "prob": 0.7013, "cuota": 1.8, "ev": 0.2623, "gano": 0, "lado": "over"}, {"fecha": "2026-02-11", "prob": 0.6852, "cuota": 2.25, "ev": 0.5417, "gano": 0, "lado": "under"}, {"fecha": "2026-02-11", "prob": 0.7003, "cuota": 1.61, "ev": 0.1276, "gano": 1, "lado": "over"}, {"fecha": "2026-02-13", "prob": 0.5199, "cuota": 3.12, "ev": 0.6222, "gano": 0, "lado": "under"}, {"fecha": "2026-02-14", "prob": 0.622, "cuota": 2.78, "ev": 0.7292, "gano": 0, "lado": "under"}, {"fecha": "2026-02-14", "prob": 0.6452, "cuota": 1.74, "ev": 0.1227, "gano": 1, "lado": "over"}, {"fecha": "2026-02-14", "prob": 0.6567, "cuota": 1.74, "ev": 0.1426, "gano": 0, "lado": "under"}, {"fecha": "2026-02-14", "prob": 0.7038, "cuota": 1.82, "ev": 0.2809, "gano": 1, "lado": "under"}, {"fecha": "2026-02-15", "prob": 0.427, "cuota": 2.52, "ev": 0.0761, "gano": 0, "lado": "under"}, {"fecha": "2026-02-17", "prob": 0.5571, "cuota": 2.32, "ev": 0.2924, "gano": 1, "lado": "under"}, {"fecha": "2026-02-20", "prob": 0.5599, "cuota": 1.92, "ev": 0.075, "gano": 0, "lado": "under"}, {"fecha": "2026-02-21", "prob": 0.5815, "cuota": 2.61, "ev": 0.5178, "gano": 1, "lado": "under"}, {"fecha": "2026-02-21", "prob": 0.5618, "cuota": 2.1, "ev": 0.1798, "gano": 1, "lado": "under"}, {"fecha": "2026-02-21", "prob": 0.6784, "cuota": 3.6, "ev": 1.4422, "gano": 0, "lado": "under"}, {"fecha": "2026-02-22", "prob": 0.553, "cuota": 2.24, "ev": 0.2388, "gano": 0, "lado": "under"}, {"fecha": "2026-02-22", "prob": 0.6108, "cuota": 2.14, "ev": 0.3071, "gano": 0, "lado": "under"}, {"fecha": "2026-02-22", "prob": 0.7044, "cuota": 2.42, "ev": 0.7047, "gano": 0, "lado": "under"}, {"fecha": "2026-02-22", "prob": 0.53, "cuota": 2.11, "ev": 0.1183, "gano": 1, "lado": "under"}, {"fecha": "2026-02-27", "prob": 0.6121, "cuota": 2.12, "ev": 0.2976, "gano": 0, "lado": "under"}, {"fecha": "2026-02-28", "prob": 0.6544, "cuota": 2.39, "ev": 0.5641, "gano": 0, "lado": "under"}, {"fecha": "2026-02-28", "prob": 0.5931, "cuota": 3.35, "ev": 0.9868, "gano": 0, "lado": "under"}, {"fecha": "2026-02-28", "prob": 0.476, "cuota": 2.84, "ev": 0.3518, "gano": 0, "lado": "under"}, {"fecha": "2026-03-01", "prob": 0.8069, "cuota": 2.08, "ev": 0.6783, "gano": 1, "lado": "under"}, {"fecha": "2026-03-01", "prob": 0.4845, "cuota": 2.32, "ev": 0.124, "gano": 1, "lado": "under"}, {"fecha": "2026-03-01", "prob": 0.5985, "cuota": 1.87, "ev": 0.1192, "gano": 1, "lado": "under"}, {"fecha": "2026-03-01", "prob": 0.573, "cuota": 2.08, "ev": 0.1918, "gano": 0, "lado": "under"}, {"fecha": "2026-03-01", "prob": 0.438, "cuota": 2.48, "ev": 0.0863, "gano": 1, "lado": "under"}, {"fecha": "2026-03-06", "prob": 0.5468, "cuota": 1.89, "ev": 0.0334, "gano": 1, "lado": "under"}, {"fecha": "2026-03-07", "prob": 0.7056, "cuota": 2.18, "ev": 0.5381, "gano": 0, "lado": "under"}, {"fecha": "2026-03-07", "prob": 0.7143, "cuota": 2.23, "ev": 0.593, "gano": 0, "lado": "under"}, {"fecha": "2026-03-08", "prob": 0.8114, "cuota": 2.19, "ev": 0.777, "gano": 0, "lado": "under"}, {"fecha": "2026-03-08", "prob": 0.5657, "cuota": 2.58, "ev": 0.4594, "gano": 0, "lado": "under"}, {"fecha": "2026-03-08", "prob": 0.7286, "cuota": 2.16, "ev": 0.5737, "gano": 0, "lado": "under"}, {"fecha": "2026-03-08", "prob": 0.5879, "cuota": 2.85, "ev": 0.6754, "gano": 0, "lado": "under"}, {"fecha": "2026-03-08", "prob": 0.5455, "cuota": 2.63, "ev": 0.4345, "gano": 1, "lado": "under"}, {"fecha": "2026-03-13", "prob": 0.813, "cuota": 2.15, "ev": 0.7479, "gano": 1, "lado": "under"}, {"fecha": "2026-03-14", "prob": 0.5238, "cuota": 2.41, "ev": 0.2623, "gano": 0, "lado": "under"}, {"fecha": "2026-03-14", "prob": 0.4949, "cuota": 2.69, "ev": 0.3313, "gano": 0, "lado": "under"}, {"fecha": "2026-03-14", "prob": 0.6139, "cuota": 3.63, "ev": 1.2284, "gano": 0, "lado": "under"}, {"fecha": "2026-03-14", "prob": 0.4929, "cuota": 2.13, "ev": 0.0498, "gano": 0, "lado": "under"}, {"fecha": "2026-03-15", "prob": 0.6521, "cuota": 2.81, "ev": 0.8324, "gano": 0, "lado": "under"}, {"fecha": "2026-03-15", "prob": 0.4203, "cuota": 2.9, "ev": 0.2188, "gano": 0, "lado": "under"}, {"fecha": "2026-03-15", "prob": 0.7768, "cuota": 1.97, "ev": 0.5303, "gano": 0, "lado": "under"}, {"fecha": "2026-03-15", "prob": 0.7515, "cuota": 2.2, "ev": 0.6532, "gano": 1, "lado": "under"}, {"fecha": "2026-03-20", "prob": 0.8398, "cuota": 2.12, "ev": 0.7804, "gano": 1, "lado": "under"}, {"fecha": "2026-03-21", "prob": 0.4085, "cuota": 2.57, "ev": 0.0499, "gano": 0, "lado": "under"}, {"fecha": "2026-03-21", "prob": 0.6184, "cuota": 2.48, "ev": 0.5336, "gano": 1, "lado": "under"}, {"fecha": "2026-03-21", "prob": 0.5784, "cuota": 2.02, "ev": 0.1683, "gano": 0, "lado": "under"}, {"fecha": "2026-03-22", "prob": 0.5891, "cuota": 2.47, "ev": 0.455, "gano": 1, "lado": "under"}, {"fecha": "2026-03-22", "prob": 0.8122, "cuota": 2.42, "ev": 0.9656, "gano": 0, "lado": "under"}, {"fecha": "2026-03-22", "prob": 0.6156, "cuota": 2.97, "ev": 0.8283, "gano": 0, "lado": "under"}, {"fecha": "2026-03-22", "prob": 0.3858, "cuota": 3.32, "ev": 0.2808, "gano": 0, "lado": "under"}, {"fecha": "2026-03-22", "prob": 0.5075, "cuota": 2.2, "ev": 0.1166, "gano": 1, "lado": "under"}, {"fecha": "2026-04-04", "prob": 0.7688, "cuota": 2.92, "ev": 1.245, "gano": 1, "lado": "under"}, {"fecha": "2026-04-04", "prob": 0.7735, "cuota": 2.56, "ev": 0.9801, "gano": 0, "lado": "under"}, {"fecha": "2026-04-04", "prob": 0.5367, "cuota": 2.42, "ev": 0.2987, "gano": 1, "lado": "under"}, {"fecha": "2026-04-04", "prob": 0.5483, "cuota": 3.17, "ev": 0.7383, "gano": 0, "lado": "under"}, {"fecha": "2026-04-04", "prob": 0.5041, "cuota": 2.35, "ev": 0.1846, "gano": 1, "lado": "under"}, {"fecha": "2026-04-05", "prob": 0.6851, "cuota": 2.47, "ev": 0.6923, "gano": 0, "lado": "under"}, {"fecha": "2026-04-05", "prob": 0.698, "cuota": 2.89, "ev": 1.0172, "gano": 0, "lado": "under"}, {"fecha": "2026-04-05", "prob": 0.6109, "cuota": 2.08, "ev": 0.2706, "gano": 1, "lado": "under"}, {"fecha": "2026-04-05", "prob": 0.4438, "cuota": 2.52, "ev": 0.1183, "gano": 1, "lado": "under"}, {"fecha": "2026-04-10", "prob": 0.3183, "cuota": 3.37, "ev": 0.0726, "gano": 0, "lado": "under"}, {"fecha": "2026-04-11", "prob": 0.5601, "cuota": 2.51, "ev": 0.4058, "gano": 1, "lado": "under"}, {"fecha": "2026-04-11", "prob": 0.4563, "cuota": 2.63, "ev": 0.2002, "gano": 0, "lado": "under"}, {"fecha": "2026-04-11", "prob": 0.3931, "cuota": 3.27, "ev": 0.2855, "gano": 1, "lado": "under"}, {"fecha": "2026-04-11", "prob": 0.6401, "cuota": 2.47, "ev": 0.581, "gano": 0, "lado": "under"}, {"fecha": "2026-04-12", "prob": 0.6651, "cuota": 1.93, "ev": 0.2837, "gano": 1, "lado": "under"}, {"fecha": "2026-04-12", "prob": 0.5484, "cuota": 2.56, "ev": 0.4039, "gano": 1, "lado": "under"}, {"fecha": "2026-04-12", "prob": 0.8426, "cuota": 2.12, "ev": 0.7862, "gano": 0, "lado": "under"}, {"fecha": "2026-04-22", "prob": 0.8018, "cuota": 2.34, "ev": 0.8762, "gano": 0, "lado": "under"}, {"fecha": "2026-04-23", "prob": 0.4579, "cuota": 2.71, "ev": 0.2409, "gano": 1, "lado": "under"}, {"fecha": "2026-04-23", "prob": 0.4513, "cuota": 3.99, "ev": 0.8006, "gano": 0, "lado": "under"}, {"fecha": "2026-04-25", "prob": 0.54, "cuota": 2.4, "ev": 0.2959, "gano": 0, "lado": "under"}, {"fecha": "2026-04-25", "prob": 0.6163, "cuota": 3.03, "ev": 0.8673, "gano": 0, "lado": "under"}, {"fecha": "2026-04-25", "prob": 0.5898, "cuota": 2.2, "ev": 0.2976, "gano": 1, "lado": "under"}, {"fecha": "2026-04-26", "prob": 0.5234, "cuota": 2.08, "ev": 0.0888, "gano": 0, "lado": "under"}, {"fecha": "2026-04-26", "prob": 0.5363, "cuota": 2.23, "ev": 0.196, "gano": 1, "lado": "under"}, {"fecha": "2026-05-02", "prob": 0.4563, "cuota": 3.08, "ev": 0.4054, "gano": 0, "lado": "under"}, {"fecha": "2026-05-02", "prob": 0.7452, "cuota": 2.29, "ev": 0.7065, "gano": 0, "lado": "under"}, {"fecha": "2026-05-02", "prob": 0.3596, "cuota": 2.94, "ev": 0.0573, "gano": 1, "lado": "under"}, {"fecha": "2026-05-02", "prob": 0.6217, "cuota": 2.19, "ev": 0.3614, "gano": 1, "lado": "under"}, {"fecha": "2026-05-03", "prob": 0.3986, "cuota": 2.67, "ev": 0.0643, "gano": 0, "lado": "under"}, {"fecha": "2026-05-03", "prob": 0.7605, "cuota": 1.5, "ev": 0.1407, "gano": 1, "lado": "over"}, {"fecha": "2026-05-03", "prob": 0.6073, "cuota": 2.54, "ev": 0.5426, "gano": 0, "lado": "under"}, {"fecha": "2026-05-03", "prob": 0.8825, "cuota": 1.46, "ev": 0.2885, "gano": 0, "lado": "over"}, {"fecha": "2026-05-03", "prob": 0.5288, "cuota": 2.58, "ev": 0.3642, "gano": 1, "lado": "under"}, {"fecha": "2026-05-10", "prob": 0.4046, "cuota": 2.54, "ev": 0.0276, "gano": 0, "lado": "under"}, {"fecha": "2026-05-10", "prob": 0.6993, "cuota": 1.61, "ev": 0.1258, "gano": 0, "lado": "over"}, {"fecha": "2026-05-10", "prob": 0.4985, "cuota": 2.46, "ev": 0.2263, "gano": 1, "lado": "under"}, {"fecha": "2026-05-10", "prob": 0.4762, "cuota": 2.32, "ev": 0.1049, "gano": 0, "lado": "under"}, {"fecha": "2026-05-10", "prob": 0.3963, "cuota": 3.64, "ev": 0.4426, "gano": 0, "lado": "under"}, {"fecha": "2026-05-10", "prob": 0.6583, "cuota": 2.32, "ev": 0.5272, "gano": 0, "lado": "under"}, {"fecha": "2026-05-10", "prob": 0.685, "cuota": 2.48, "ev": 0.6989, "gano": 1, "lado": "under"}, {"fecha": "2026-05-10", "prob": 0.3861, "cuota": 2.73, "ev": 0.0539, "gano": 0, "lado": "under"}, {"fecha": "2026-05-17", "prob": 0.3571, "cuota": 3.38, "ev": 0.2071, "gano": 0, "lado": "under"}, {"fecha": "2026-05-17", "prob": 0.5724, "cuota": 2.4, "ev": 0.3738, "gano": 0, "lado": "under"}, {"fecha": "2026-05-17", "prob": 0.6432, "cuota": 3.85, "ev": 1.4762, "gano": 0, "lado": "under"}, {"fecha": "2026-05-17", "prob": 0.6133, "cuota": 3.75, "ev": 1.2999, "gano": 0, "lado": "under"}, {"fecha": "2026-05-17", "prob": 0.685, "cuota": 2.4, "ev": 0.6441, "gano": 0, "lado": "under"}, {"fecha": "2026-05-17", "prob": 0.6061, "cuota": 2.78, "ev": 0.6849, "gano": 1, "lado": "under"}, {"fecha": "2026-05-17", "prob": 0.6513, "cuota": 2.07, "ev": 0.3482, "gano": 0, "lado": "under"}, {"fecha": "2026-05-17", "prob": 0.3356, "cuota": 3.0, "ev": 0.0067, "gano": 1, "lado": "under"}]